timeshap/__init__.py
timeshap/version.py
timeshap/explainer/__init__.py
timeshap/explainer/cell_level.py
timeshap/explainer/event_level.py
timeshap/explainer/feature_level.py
timeshap/explainer/global_methods.py
timeshap/explainer/local_methods.py
timeshap/explainer/pruning.py
timeshap/explainer/kernel/__init__.py
timeshap/explainer/kernel/timeshap_kernel.py
timeshap/plot/__init__.py
timeshap/plot/cell_level.py
timeshap/plot/event_level.py
timeshap/plot/feature_level.py
timeshap/plot/global_report.py
timeshap/plot/local_report.py
timeshap/plot/pruning.py
timeshap/plot/utils.py
timeshap/utils/__init__.py
timeshap/utils/compatibility.py
timeshap/utils/timeshap_legacy.py
timeshap/utils/utils.py
timeshap/wrappers/__init__.py
timeshap/wrappers/base_wrapper.py
timeshap/wrappers/tf_wrappers.py
timeshap/wrappers/torch_wrappers.py
timeshap-1.0.4.dist-info/LICENSE
timeshap-1.0.4.dist-info/METADATA
timeshap-1.0.4.dist-info/WHEEL
timeshap-1.0.4.dist-info/top_level.txt
timeshap-1.0.4.dist-info/RECORD
