Metadata-Version: 2.1
Name: timeshap
Version: 1.0.4
Summary: KernelSHAP adaptation for recurrent models.
Home-page: https://github.com/feedzai/timeshap
Author: Feedzai
Keywords: explainability,TimeShap
Requires-Python: >=3.6
License-File: LICENSE
Requires-Dist: pandas >=1.3.2
Requires-Dist: scikit-learn >=0.23.2
Requires-Dist: seaborn >=0.11.1
Requires-Dist: matplotlib >=3.3.2
Requires-Dist: numpy >=1.19.2
Requires-Dist: shap >=0.37.0
Requires-Dist: scipy >=1.5.2
Requires-Dist: plotly >=4.6
Requires-Dist: seaborn >=0.11.2
Requires-Dist: altair
Requires-Dist: feedzai-altair-theme
